transitions_gui/__init__.py
transitions_gui/__init__.pyi
transitions_gui/py.typed
transitions_gui/settings.py
transitions_gui/settings.pyi
transitions_gui/version.py
transitions_gui/version.pyi
transitions_gui/web.py
transitions_gui/web.pyi
transitions_gui/handlers/__init__.py
transitions_gui/handlers/__init__.pyi
transitions_gui/static/thirdpartynotice.txt
transitions_gui/static/css/style.css
transitions_gui/static/img/pencil.svg
transitions_gui/static/img/save.svg
transitions_gui/static/js/main.js
transitions_gui/static/js/main.js.LICENSE.txt
transitions_gui/static/js/main.js.map
transitions_gui/templates/index.html
transitions_gui-0.9.0.dist-info/LICENSE
transitions_gui-0.9.0.dist-info/METADATA
transitions_gui-0.9.0.dist-info/WHEEL
transitions_gui-0.9.0.dist-info/top_level.txt
transitions_gui-0.9.0.dist-info/RECORD
