Metadata-Version: 2.1
Name: transitions-gui
Version: 0.9.0
Summary: A frontend for the state machine library transitions
Home-page: http://github.com/pytransitions/transitions-gui
Download-URL: https://github.com/pytransitions/transitions-gui/archive/0.9.0.tar.gz
Author: Alexander Neumann
Author-email: aleneum@gmail.com
License: MIT
Classifier: License :: OSI Approved :: MIT License
Classifier: Programming Language :: Python :: 2
Classifier: Programming Language :: Python :: 2.7
Classifier: Programming Language :: Python :: 3
Classifier: Programming Language :: Python :: 3.7
Classifier: Programming Language :: Python :: 3.8
Classifier: Programming Language :: Python :: 3.9
Classifier: Programming Language :: Python :: 3.10
Classifier: Programming Language :: Python :: 3.11
Classifier: Programming Language :: Python :: 3.12
License-File: LICENSE
Requires-Dist: tornado >=5.0
Requires-Dist: transitions >=0.9.0
